code.v
module apb(
  input pclk,
  input presetn,

  input [1:0] psel,
  input pwrite,
  input penable,

  input [3:0] pwdata,
  input [3:0] paddr,

  input [3:0] prdata0,
  input [3:0] prdata1,
  input [3:0] prdata2,

  output reg [3:0] data,
  output reg pready
);

always @(posedge pclk or negedge presetn)
begin
  if (!presetn)
  begin
    data   <= 0;
    pready <= 0;
  end
  else
  begin
    if (|psel && !penable)
    begin
      pready <= 0;
    end
    else if (|psel && penable)
    begin
      case (psel)
        2'b00: begin
          if (pwrite)
            data <= pwdata;     // WRITE
          else
            data <= prdata0;    // READ
        end
        2'b01: begin
          if (pwrite)
            data <= pwdata;
          else
            data <= prdata1;
        end
        2'b10: begin
          if (pwrite)
            data <= pwdata;
          else
            data <= prdata2;
        end
        2'b11: begin
          if (pwrite)
            data <= pwdata;
          else
            data <= prdata2;
        end
        default: data <= 0;

      endcase

      pready <= 1; 
    end
    else
    begin
      pready <= 0;
    end
  end
end

endmodule

apb_tb.v
module tb_apb;

  reg pclk, presetn;
  reg [1:0] psel;
  reg pwrite, penable;
  reg [3:0] pwdata, paddr;

  reg [3:0] prdata0, prdata1, prdata2;

  wire [3:0] data;
  wire pready;

  // DUT Instantiation
  apb uut (
    .pclk(pclk),
    .presetn(presetn),
    .psel(psel),
    .pwrite(pwrite),
    .penable(penable),
    .pwdata(pwdata),
    .paddr(paddr),
    .prdata0(prdata0),
    .prdata1(prdata1),
    .prdata2(prdata2),
    .data(data),
    .pready(pready)
  );

  // Clock generation
  always #5 pclk = ~pclk;

  initial begin
    $dumpfile("apb.vcd");
    $dumpvars(0, tb_apb);

    // Initial values
    pclk    = 0;
    presetn = 0;
    psel    = 2'b00;
    pwrite  = 0;
    penable = 0;
    pwdata  = 4'h0;
    paddr   = 4'h0;

    prdata0 = 4'hA;
    prdata1 = 4'hB;
    prdata2 = 4'hC;

    // Reset
    #10 presetn = 1;

    // Write to Slave 0
    @(posedge pclk);
    psel    = 2'b00;
    pwrite  = 1;
    pwdata  = 4'h5;
    penable = 0;

    @(posedge pclk);
    penable = 1;

    // Read from Slave 0
    @(posedge pclk);
    pwrite  = 0;
    penable = 0;

    @(posedge pclk);
    penable = 1;

    @(posedge pclk);
    psel    = 2'b01;
    pwrite  = 1;
    pwdata  = 4'h6;
    penable = 0;

    @(posedge pclk);
    penable = 1;

    @(posedge pclk);
    pwrite  = 0;
    penable = 0;

    @(posedge pclk);
    penable = 1;

    @(posedge pclk);
    psel    = 2'b10;
    pwrite  = 1;
    pwdata  = 4'h9;
    penable = 0;

    @(posedge pclk);
    penable = 1;

    @(posedge pclk);
    pwrite  = 0;
    penable = 0;

    @(posedge pclk);
    penable = 1;

    @(posedge pclk);
    psel    = 2'b11;
    pwrite  = 1;
    pwdata  = 4'hF;
    penable = 0;

    @(posedge pclk);
    penable = 1;

    @(posedge pclk);
    pwrite  = 0;
    penable = 0;

    @(posedge pclk);
    penable = 1;

    // End
    #20;
    $finish;
  end

endmodule

apb.vcd
$date
	Sat May  2 19:08:35 2026
$end
$version
	Icarus Verilog
$end
$timescale
	1s
$end
$scope module tb_apb $end
$var wire 1 ! pready $end
$var wire 4 " data [3:0] $end
$var reg 4 # paddr [3:0] $end
$var reg 1 $ pclk $end
$var reg 1 % penable $end
$var reg 4 & prdata0 [3:0] $end
$var reg 4 ' prdata1 [3:0] $end
$var reg 4 ( prdata2 [3:0] $end
$var reg 1 ) presetn $end
$var reg 2 * psel [1:0] $end
$var reg 4 + pwdata [3:0] $end
$var reg 1 , pwrite $end
$scope module uut $end
$var wire 4 - paddr [3:0] $end
$var wire 1 $ pclk $end
$var wire 1 % penable $end
$var wire 4 . prdata0 [3:0] $end
$var wire 4 / prdata1 [3:0] $end
$var wire 4 0 prdata2 [3:0] $end
$var wire 1 ) presetn $end
$var wire 2 1 psel [1:0] $end
$var wire 4 2 pwdata [3:0] $end
$var wire 1 , pwrite $end
$var reg 4 3 data [3:0] $end
$var reg 1 ! pready $end
$upscope $end
$upscope $end
$enddefinitions $end
#0
$dumpvars
b0 3
b0 2
b0 1
b1100 0
b1011 /
b1010 .
b0 -
0,
b0 +
b0 *
0)
b1100 (
b1011 '
b1010 &
0%
0$
b0 #
b0 "
0!
$end
#5
1$
#10
0$
1)
#15
b101 +
b101 2
1,
1$
#20
0$
#25
1%
1$
#30
0$
#35
0%
0,
1$
#40
0$
#45
1%
1$
#50
0$
#55
0%
b110 +
b110 2
1,
b1 *
b1 1
1$
#60
0$
#65
1!
b110 "
b110 3
1%
1$
#70
0$
#75
0!
0%
0,
1$
#80
0$
#85
1!
b1011 "
b1011 3
1%
1$
#90
0$
#95
0!
0%
b1001 +
b1001 2
1,
b10 *
b10 1
1$
#100
0$
#105
1!
b1001 "
b1001 3
1%
1$
#110
0$
#115
0!
0%
0,
1$
#120
0$
#125
1!
b1100 "
b1100 3
1%
1$
#130
0$
#135
0!
0%
b1111 +
b1111 2
1,
b11 *
b11 1
1$
#140
0$
#145
1!
b1111 "
b1111 3
1%
1$
#150
0$
#155
0!
0%
0,
1$
#160
0$
#165
1!
b1100 "
b1100 3
1%
1$
